{
    "meter": "مستفعلن فع مستفعلن فع (متقارب مثمن اثلم)",
    "relatedSongs": [
        {
            "title": "همایون شجریان » خداوندان اسرار » تصنیف جانی و صد آه",
            "link": "https://beeptunes.com/track/68592092"
        },
        {
            "title": "سالار عقیلی » سر هزار ساله » عیش مدام",
            "link": "https://beeptunes.com/track/37865284"
        },
        {
            "title": "همایون شجریان » شوق دوست » تصنیف \"بخت سرکش\"",
            "link": "https://beeptunes.com/track/19377745"
        },
        {
            "title": "بیژن کامکار » دف و نی » عیشم مدام است",
            "link": "https://beeptunes.com/track/3431755"
        },
        {
            "title": "محمدرضا شجریان » اجراهای خصوصی » طریق کام‌بخشی – اجرای خصوصی محمدرضا شجریان و محمد موسوی",
            "link": "https://khosousi.com/tarighe-kaam-bakhshi-shajarian-mousavi/"
        },
        {
            "title": "محمدرضا شجریان » اجراهای خصوصی » مرید خرابات – اجرای خصوصی محمدرضا شجریان، فرهنگ شریف و جهانگیر ملک - اجرای ۱۲ اسفند ۱۳۶۲",
            "link": "https://khosousi.com/moride-kharabat-shaajrian-sharif-malek/"
        },
        {
            "title": "محسن کرامتی » ۱۸۶ تصنیف قدیمی ۱ » بیات اصفهان ۲",
            "link": "https://beeptunes.com/track/3449931"
        },
        {
            "title": "سپیده رئیس سادات » Persian Songs » عیش مدام",
            "link": "https://open.spotify.com/track/4QpEn3BKTXzDKKme6jhXs8"
        },
        {
            "title": "مهسا وحدت و The Secret Ensemble » Kuşların Çağrısı » Arzulanan Yakut",
            "link": "https://open.spotify.com/track/7KOoBV9CBy5C4V29nVtTSc"
        },
        {
            "title": "سلی » حمدی فیل » الحمدلله",
            "link": "https://open.spotify.com/track/6OdHrUELDz8Zouqo77XGDu"
        }
    ]
}