{
    "meter": "مفاعلن فعلاتن مفاعلن فعلن (مجتث مثمن مخبون محذوف)",
    "relatedSongs": [
        {
            "title": "برگ سبز » شمارهٔ ۱۲۱ » (چهار گاه) (۱۴:۰۸ - ۱۸:۴۰) نوازندگان: کسایی، حسن (‎نی) خواننده آواز: قوامی (فاخته‌ای)، حسین سراینده شعر آواز: حافظ شیرازی (غزل) مطلع شعر آواز: شراب و عیش نهان چیست کار بی بنیاد",
            "link": "http://www.golha.co.uk/fa/programme/131"
        },
        {
            "title": "حامد بهداد » هزار هیچ » تخت جم به باد",
            "link": "https://beeptunes.com/track/567771412"
        }
    ]
}